CliDApp4Rhino/CliDApp4Rhino
CliDApp4Rhino/CliDApp4Rhino.exe
CliDApp4Rhino/__init__.py
CliDApp4Rhino/clidapp4rhino_cmd.py
CliDApp4Rhino/run_executable.py
clidapp4rhino-1.0.24.dist-info/entry_points.txt
clidapp4rhino-1.0.24.dist-info/WHEEL
clidapp4rhino-1.0.24.dist-info/METADATA
clidapp4rhino-1.0.24.dist-info/RECORD
