Metadata-Version: 2.3
Name: CliDApp4Rhino
Version: 1.0.24
Summary: CliDApp4Rhino is a graphical user interface tool for the Rhino 3D CAD software.
Author-email: "Elizabeth Consulting International Inc." <info@ec-intl.com>
Requires-Python: >=3.8
Classifier: Programming Language :: Python :: 3
Classifier: License :: OSI Approved :: MIT License
Classifier: Operating System :: OS Independent
Project-URL: Homepage, https://github.com/ec-intl/clidapp4rhino
Project-URL: Issues, https://github.com/ec-intl/clidapp4rhino/issues
